{
    "results": [
        {
            "id": 797495,
            "title": "Homemade Chinese Doughnuts",
            "readyInMinutes": 40,
            "servings": 10,
            "image": "homemade-chinese-doughnuts-797495.jpg",
            "imageUrls": [
                "homemade-chinese-doughnuts-797495.jpg"
            ]
        },
        {
            "id": 864521,
            "title": "Deliciously Easy Healthy Donut",
            "readyInMinutes": 27,
            "servings": 12,
            "image": "deliciously-easy-healthy-donut-864521.jpg",
            "imageUrls": [
                "deliciously-easy-healthy-donut-864521.jpg"
            ]
        },
        {
            "id": 868628,
            "title": "Deliciously Easy Healthy Donut",
            "readyInMinutes": 27,
            "servings": 12,
            "image": "deliciously-easy-healthy-donut-868628.jpg",
            "imageUrls": [
                "deliciously-easy-healthy-donut-868628.jpg"
            ]
        },
        {
            "id": 775815,
            "title": "Baked Lemon Blueberry Doughnuts (Donuts)",
            "readyInMinutes": 23,
            "servings": 15,
            "image": "baked-lemon-blueberry-doughnuts-donuts-775815.jpg",
            "imageUrls": [
                "baked-lemon-blueberry-doughnuts-donuts-775815.jpg"
            ]
        },
        {
            "id": 507693,
            "title": "Vanilla Cream-Filled Doughnuts",
            "readyInMinutes": 720,
            "servings": 9,
            "image": "Vanilla-Cream-Filled-Doughnuts-507693.jpg",
            "imageUrls": [
                "Vanilla-Cream-Filled-Doughnuts-507693.jpg"
            ]
        },
        {
            "id": 573422,
            "title": "Glazed Chocolate Donut Holes",
            "readyInMinutes": 45,
            "servings": 36,
            "image": "Glazed-Chocolate-Donut-Holes-573422.jpg",
            "imageUrls": [
                "Glazed-Chocolate-Donut-Holes-573422.jpg"
            ]
        },
        {
            "id": 813033,
            "title": "Browned Butter Glazed Cinnamon Donuts",
            "readyInMinutes": 45,
            "servings": 3,
            "image": "browned-butter-glazed-cinnamon-donuts-813033.jpg",
            "imageUrls": [
                "browned-butter-glazed-cinnamon-donuts-813033.jpg"
            ]
        },
        {
            "id": 558165,
            "title": "Apple Pie Doughnuts",
            "readyInMinutes": 30,
            "servings": 8,
            "image": "Apple-Pie-Doughnuts-558165.jpg",
            "imageUrls": [
                "Apple-Pie-Doughnuts-558165.jpg"
            ]
        },
        {
            "id": 592747,
            "title": "Guest Post: Baked Nutella Doughnuts",
            "readyInMinutes": 45,
            "servings": 20,
            "image": "Guest-Post--Baked-Nutella-Doughnuts-592747.jpg",
            "imageUrls": [
                "Guest-Post--Baked-Nutella-Doughnuts-592747.jpg"
            ]
        },
        {
            "id": 610546,
            "title": "Pumpkin Doughnuts",
            "readyInMinutes": 35,
            "servings": 18,
            "image": "Pumpkin-Doughnuts-610546.jpg",
            "imageUrls": [
                "Pumpkin-Doughnuts-610546.jpg"
            ]
        },
        {
            "id": 819889,
            "title": "30 Minute Donut Holes",
            "readyInMinutes": 29,
            "servings": 36,
            "image": "30-minute-donut-holes-819889.jpg",
            "imageUrls": [
                "30-minute-donut-holes-819889.jpg"
            ]
        },
        {
            "id": 813049,
            "title": "S'mores Donuts",
            "readyInMinutes": 45,
            "servings": 3,
            "image": "smores-donuts-813049.jpg",
            "imageUrls": [
                "smores-donuts-813049.jpg"
            ]
        },
        {
            "id": 508160,
            "title": "Apple Fritter Doughnuts",
            "readyInMinutes": 240,
            "servings": 14,
            "image": "Apple-Fritter-Doughnuts-508160.jpg",
            "imageUrls": [
                "Apple-Fritter-Doughnuts-508160.jpg"
            ]
        },
        {
            "id": 893704,
            "title": "Mom's Apple Fritters",
            "readyInMinutes": 35,
            "servings": 24,
            "image": "moms-apple-fritters-893704.jpg",
            "imageUrls": [
                "moms-apple-fritters-893704.jpg"
            ]
        },
        {
            "id": 780537,
            "title": "Awesome Country Apple Fritter Bread",
            "readyInMinutes": 45,
            "servings": 8,
            "image": "awesome-country-apple-fritter-bread-780537.jpg",
            "imageUrls": [
                "awesome-country-apple-fritter-bread-780537.jpg"
            ]
        },
        {
            "id": 558034,
            "title": "Nutella Stuffed Donut Holes",
            "readyInMinutes": 28,
            "servings": 24,
            "image": "Nutella-Stuffed-Donut-Holes-558034.jpg",
            "imageUrls": [
                "Nutella-Stuffed-Donut-Holes-558034.jpg"
            ]
        },
        {
            "id": 590391,
            "title": "Fruit-Filled Puff Pastry Donuts with Lemon Glaze",
            "readyInMinutes": 45,
            "servings": 12,
            "image": "Fruit-Filled-Puff-Pastry-Donuts-with-Lemon-Glaze-590391.jpg",
            "imageUrls": [
                "Fruit-Filled-Puff-Pastry-Donuts-with-Lemon-Glaze-590391.jpg"
            ]
        },
        {
            "id": 825474,
            "title": "Baked Banana Nut Donuts - Hello HealthyHello Healthy",
            "readyInMinutes": 45,
            "servings": 6,
            "image": "baked-banana-nut-donuts-hello-healthyhello-healthy-825474.jpg",
            "imageUrls": [
                "baked-banana-nut-donuts-hello-healthyhello-healthy-825474.jpg"
            ]
        },
        {
            "id": 818233,
            "title": "Double Glazed Funfetti Donuts",
            "readyInMinutes": 45,
            "servings": 5,
            "image": "double-glazed-funfetti-donuts-818233.jpg",
            "imageUrls": [
                "double-glazed-funfetti-donuts-818233.jpg"
            ]
        },
        {
            "id": 830165,
            "title": "Costas French Market Doughnuts (Beignets)",
            "readyInMinutes": 90,
            "servings": 12,
            "image": "costas-french-market-doughnuts-beignets-830165.jpg",
            "imageUrls": [
                "costas-french-market-doughnuts-beignets-830165.jpg"
            ]
        },
        {
            "id": 590295,
            "title": "Baked Cinnamon Sugar Doughnuts",
            "readyInMinutes": 45,
            "servings": 18,
            "image": "Baked-Cinnamon-Sugar-Doughnuts-590295.jpg",
            "imageUrls": [
                "Baked-Cinnamon-Sugar-Doughnuts-590295.jpg"
            ]
        },
        {
            "id": 474924,
            "title": "Baked Pumpkin Doughnuts with Maple-Cinnamon Glaze",
            "readyInMinutes": 45,
            "servings": 12,
            "image": "Baked-Pumpkin-Doughnuts-with-Maple-Cinnamon-Glaze-474924.jpg",
            "imageUrls": [
                "Baked-Pumpkin-Doughnuts-with-Maple-Cinnamon-Glaze-474924.jpg"
            ]
        },
        {
            "id": 575839,
            "title": "The BEST Cake Donuts",
            "readyInMinutes": 20,
            "servings": 12,
            "image": "The-BEST-Cake-Donuts-575839.jpg",
            "imageUrls": [
                "The-BEST-Cake-Donuts-575839.jpg"
            ]
        },
        {
            "id": 875116,
            "title": "Baked Doughnuts",
            "readyInMinutes": 45,
            "servings": 12,
            "image": "baked-doughnuts-875116.jpg",
            "imageUrls": [
                "baked-doughnuts-875116.jpg"
            ]
        },
        {
            "id": 558123,
            "title": "Chocolate Donuts (Baked!)",
            "readyInMinutes": 25,
            "servings": 10,
            "image": "Chocolate-Donuts-(Baked)-558123.jpg",
            "imageUrls": [
                "Chocolate-Donuts-(Baked)-558123.jpg"
            ]
        },
        {
            "id": 540479,
            "title": "Easy Lemon Donut Holes {two ways}",
            "readyInMinutes": 45,
            "servings": 32,
            "image": "Easy-Lemon-Donut-Holes-{two-ways}-540479.jpg",
            "imageUrls": [
                "Easy-Lemon-Donut-Holes-{two-ways}-540479.jpg"
            ]
        },
        {
            "id": 558379,
            "title": "Eggnog Donuts (Baked)",
            "readyInMinutes": 20,
            "servings": 10,
            "image": "Eggnog-Donuts-(Baked)-558379.jpg",
            "imageUrls": [
                "Eggnog-Donuts-(Baked)-558379.jpg"
            ]
        },
        {
            "id": 573465,
            "title": "Apple Cider Donut Holes",
            "readyInMinutes": 45,
            "servings": 14,
            "image": "Apple-Cider-Donut-Holes-573465.jpg",
            "imageUrls": [
                "Apple-Cider-Donut-Holes-573465.jpg"
            ]
        },
        {
            "id": 575819,
            "title": "Glazed Blueberry Donuts",
            "readyInMinutes": 45,
            "servings": 6,
            "image": "Glazed-Blueberry-Donuts-575819.jpg",
            "imageUrls": [
                "Glazed-Blueberry-Donuts-575819.jpg"
            ]
        },
        {
            "id": 524395,
            "title": "Baked Cinnamon Donuts",
            "readyInMinutes": 45,
            "servings": 12,
            "image": "Baked-Cinnamon-Donuts-524395.jpg",
            "imageUrls": [
                "Baked-Cinnamon-Donuts-524395.jpg"
            ]
        },
        {
            "id": 509155,
            "title": "Chocolate Coffee Banana Donuts",
            "readyInMinutes": 35,
            "servings": 6,
            "image": "Chocolate-Coffee-Banana-Donuts-509155.png",
            "imageUrls": [
                "Chocolate-Coffee-Banana-Donuts-509155.png"
            ]
        },
        {
            "id": 992138,
            "title": "Gluten-free Pumpkin Donuts (paleo, grain-free, dairy-free)",
            "readyInMinutes": 88,
            "servings": 30,
            "image": "gluten-free-pumpkin-donuts-paleo-grain-free-dairy-free-992138.jpg",
            "imageUrls": [
                "gluten-free-pumpkin-donuts-paleo-grain-free-dairy-free-992138.jpg"
            ]
        },
        {
            "id": 559431,
            "title": "Cherry Jam Filled Sour Cream Donuts",
            "readyInMinutes": 45,
            "servings": 24,
            "image": "Cherry-Jam-Filled-Sour-Cream-Donuts-559431.jpg",
            "imageUrls": [
                "Cherry-Jam-Filled-Sour-Cream-Donuts-559431.jpg"
            ]
        },
        {
            "id": 558213,
            "title": "Chocolate Donuts (Baked!)",
            "readyInMinutes": 25,
            "servings": 10,
            "image": "Chocolate-Donuts-(Baked)-558213.jpg",
            "imageUrls": [
                "Chocolate-Donuts-(Baked)-558213.jpg"
            ]
        },
        {
            "id": 732841,
            "title": "Apple Fritters",
            "readyInMinutes": 35,
            "servings": 30,
            "image": "apple-fritters-732841.jpeg",
            "imageUrls": [
                "apple-fritters-732841.jpeg"
            ]
        },
        {
            "id": 696347,
            "title": "Pumpkin Doughnuts",
            "readyInMinutes": 120,
            "servings": 12,
            "image": "pumpkin-doughnuts-696347.jpg",
            "imageUrls": [
                "pumpkin-doughnuts-696347.jpg"
            ]
        },
        {
            "id": 474898,
            "title": "Baked Key Lime Pie Donuts {Key Lime Blog Party}",
            "readyInMinutes": 30,
            "servings": 14,
            "image": "Baked-Key-Lime-Pie-Donuts-{Key-Lime-Blog-Party}-474898.jpg",
            "imageUrls": [
                "Baked-Key-Lime-Pie-Donuts-{Key-Lime-Blog-Party}-474898.jpg"
            ]
        },
        {
            "id": 569840,
            "title": "Chocolate Frosted Doughnuts",
            "readyInMinutes": 45,
            "servings": 6,
            "image": "Chocolate-Frosted-Doughnuts-569840.jpg",
            "imageUrls": [
                "Chocolate-Frosted-Doughnuts-569840.jpg"
            ]
        },
        {
            "id": 673355,
            "title": "Jelly Doughnut",
            "readyInMinutes": 45,
            "servings": 18,
            "image": "Jelly-Doughnut-673355.jpg",
            "imageUrls": [
                "Jelly-Doughnut-673355.jpg"
            ]
        },
        {
            "id": 535659,
            "title": "Mini Samoa Donuts",
            "readyInMinutes": 30,
            "servings": 12,
            "image": "Mini-Samoa-Donuts-535659.jpg",
            "imageUrls": [
                "Mini-Samoa-Donuts-535659.jpg"
            ]
        },
        {
            "id": 973600,
            "title": "Grain Free Chocolate Donuts",
            "readyInMinutes": 20,
            "servings": 12,
            "image": "grain-free-chocolate-donuts-973600.jpg",
            "imageUrls": [
                "grain-free-chocolate-donuts-973600.jpg"
            ]
        },
        {
            "id": 490396,
            "title": "Chocolate Mint Donuts",
            "readyInMinutes": 24,
            "servings": 16,
            "image": "Chocolate-Mint-Donuts-490396.jpg",
            "imageUrls": [
                "Chocolate-Mint-Donuts-490396.jpg"
            ]
        },
        {
            "id": 868629,
            "title": "Baked doughnuts",
            "readyInMinutes": 45,
            "servings": 6,
            "image": "baked-doughnuts-868629.jpg",
            "imageUrls": [
                "baked-doughnuts-868629.jpg"
            ]
        },
        {
            "id": 575829,
            "title": "Fluffernutter Baked Donuts",
            "readyInMinutes": 18,
            "servings": 6,
            "image": "Fluffernutter-Baked-Donuts-575829.jpg",
            "imageUrls": [
                "Fluffernutter-Baked-Donuts-575829.jpg"
            ]
        },
        {
            "id": 591794,
            "title": "Old-Fashioned Sour Cream Doughnuts",
            "readyInMinutes": 45,
            "servings": 12,
            "image": "Old-Fashioned-Sour-Cream-Doughnuts-591794.jpg",
            "imageUrls": [
                "Old-Fashioned-Sour-Cream-Doughnuts-591794.jpg"
            ]
        },
        {
            "id": 549419,
            "title": "Miss Shortcake-Gordough’s Donuts",
            "readyInMinutes": 10,
            "servings": 8,
            "image": "Miss-Shortcake-Gordoughs-Donuts-549419.jpg",
            "imageUrls": [
                "Miss-Shortcake-Gordoughs-Donuts-549419.jpg"
            ]
        },
        {
            "id": 484033,
            "title": "Homemade Donuts",
            "readyInMinutes": 160,
            "servings": 15,
            "image": "Homemade-Donuts-484033.jpg",
            "imageUrls": [
                "Homemade-Donuts-484033.jpg"
            ]
        },
        {
            "id": 496243,
            "title": "Gluten Free Red Velvet Donuts",
            "readyInMinutes": 20,
            "servings": 7,
            "image": "Gluten-Free-Red-Velvet-Donuts-496243.jpg",
            "imageUrls": [
                "Gluten-Free-Red-Velvet-Donuts-496243.jpg"
            ]
        },
        {
            "id": 608559,
            "title": "Peanut Butter Cream Doughnuts",
            "readyInMinutes": 45,
            "servings": 8,
            "image": "Peanut-Butter-Cream-Doughnuts-608559.jpg",
            "imageUrls": [
                "Peanut-Butter-Cream-Doughnuts-608559.jpg"
            ]
        },
        {
            "id": 578314,
            "title": "Krispy Kreme Glazed Donut",
            "readyInMinutes": 70,
            "servings": 12,
            "image": "Krispy-Kreme-Glazed-Donut-578314.jpg",
            "imageUrls": [
                "Krispy-Kreme-Glazed-Donut-578314.jpg"
            ]
        },
        {
            "id": 573560,
            "title": "Baked Banana Bread Donuts with Dark Chocolate Glaze",
            "readyInMinutes": 45,
            "servings": 8,
            "image": "Baked-Banana-Bread-Donuts-with-Dark-Chocolate-Glaze-573560.jpg",
            "imageUrls": [
                "Baked-Banana-Bread-Donuts-with-Dark-Chocolate-Glaze-573560.jpg"
            ]
        },
        {
            "id": 472770,
            "title": "Glazed Chocolate Donut Holes",
            "readyInMinutes": 25,
            "servings": 9,
            "image": "Glazed-Chocolate-Donut-Holes-472770.jpg",
            "imageUrls": [
                "Glazed-Chocolate-Donut-Holes-472770.jpg"
            ]
        },
        {
            "id": 626745,
            "title": "Vanilla Baked Donuts with Fresh Raspberry Glaze",
            "readyInMinutes": 43,
            "servings": 12,
            "image": "Vanilla-Baked-Donuts-with-Fresh-Raspberry-Glaze-626745.jpg",
            "imageUrls": [
                "Vanilla-Baked-Donuts-with-Fresh-Raspberry-Glaze-626745.jpg"
            ]
        },
        {
            "id": 473485,
            "title": "Carrot Cake Baked Donuts",
            "readyInMinutes": 45,
            "servings": 6,
            "image": "carrot-cake-baked-donuts-473485.jpg",
            "imageUrls": [
                "carrot-cake-baked-donuts-473485.jpg"
            ]
        },
        {
            "id": 583839,
            "title": "Candied Maple Bacon Donut",
            "readyInMinutes": 45,
            "servings": 12,
            "image": "Candied-Maple-Bacon-Donut-583839.jpg",
            "imageUrls": [
                "Candied-Maple-Bacon-Donut-583839.jpg"
            ]
        },
        {
            "id": 579114,
            "title": "Maple Bacon Donuts",
            "readyInMinutes": 90,
            "servings": 6,
            "image": "Maple-Bacon-Donuts-579114.jpg",
            "imageUrls": [
                "Maple-Bacon-Donuts-579114.jpg"
            ]
        },
        {
            "id": 588442,
            "title": "Chocolate donuts with coconut vanilla bean icing",
            "readyInMinutes": 22,
            "servings": 8,
            "image": "Chocolate-donuts-with-coconut-vanilla-bean-icing-588442.jpg",
            "imageUrls": [
                "Chocolate-donuts-with-coconut-vanilla-bean-icing-588442.jpg"
            ]
        },
        {
            "id": 583759,
            "title": "Cinnamon Sugar Donuts",
            "readyInMinutes": 45,
            "servings": 18,
            "image": "Cinnamon-Sugar-Donuts-583759.jpg",
            "imageUrls": [
                "Cinnamon-Sugar-Donuts-583759.jpg"
            ]
        },
        {
            "id": 992399,
            "title": "Cinnamon “Sugar” Mini Doughnuts – Low Carb",
            "readyInMinutes": 20,
            "servings": 12,
            "image": "cinnamon-sugar-mini-doughnuts-low-carb-992399.jpg",
            "imageUrls": [
                "cinnamon-sugar-mini-doughnuts-low-carb-992399.jpg"
            ]
        },
        {
            "id": 848192,
            "title": "Baked Lemon Blueberry Donuts",
            "readyInMinutes": 30,
            "servings": 8,
            "image": "baked-lemon-blueberry-donuts-848192.jpg",
            "imageUrls": [
                "baked-lemon-blueberry-donuts-848192.jpg"
            ]
        },
        {
            "id": 587475,
            "title": "Pumpkin Spice Donuts with Maple Almond Butter Glaze",
            "readyInMinutes": 20,
            "servings": 12,
            "image": "Pumpkin-Spice-Donuts-with-Maple-Almond-Butter-Glaze-587475.jpg",
            "imageUrls": [
                "Pumpkin-Spice-Donuts-with-Maple-Almond-Butter-Glaze-587475.jpg"
            ]
        },
        {
            "id": 521215,
            "title": "Baked apple donuts with cinnamon and nutmeg",
            "readyInMinutes": 40,
            "servings": 9,
            "image": "Baked-apple-donuts-with-cinnamon-and-nutmeg-521215.jpg",
            "imageUrls": [
                "Baked-apple-donuts-with-cinnamon-and-nutmeg-521215.jpg"
            ]
        },
        {
            "id": 490601,
            "title": "Chocolate Pumpkin Spider Donuts",
            "readyInMinutes": 19,
            "servings": 24,
            "image": "chocolate-pumpkin-spider-donuts-490601.jpg",
            "imageUrls": [
                "chocolate-pumpkin-spider-donuts-490601.jpg"
            ]
        },
        {
            "id": 509756,
            "title": "Chocolate Strawberry Donuts",
            "readyInMinutes": 35,
            "servings": 6,
            "image": "Chocolate-Strawberry-Donuts-509756.jpg",
            "imageUrls": [
                "Chocolate-Strawberry-Donuts-509756.jpg"
            ]
        },
        {
            "id": 473688,
            "title": "Baked Red Velvet Donuts {Red Velvet Week}",
            "readyInMinutes": 30,
            "servings": 12,
            "image": "Baked-Red-Velvet-Donuts-{Red-Velvet-Week}-473688.jpg",
            "imageUrls": [
                "Baked-Red-Velvet-Donuts-{Red-Velvet-Week}-473688.jpg"
            ]
        },
        {
            "id": 807279,
            "title": "Skinny Cream Cheese Glazed Pumpkin Donuts",
            "readyInMinutes": 20,
            "servings": 12,
            "image": "skinny-cream-cheese-glazed-pumpkin-donuts-807279.jpg",
            "imageUrls": [
                "skinny-cream-cheese-glazed-pumpkin-donuts-807279.jpg"
            ]
        },
        {
            "id": 595805,
            "title": "Boston Cream Delight",
            "readyInMinutes": 150,
            "servings": 15,
            "image": "Boston-Cream-Delight-595805.jpg",
            "imageUrls": [
                "Boston-Cream-Delight-595805.jpg"
            ]
        },
        {
            "id": 481699,
            "title": "Baked Pumpkin Donuts with Caramel Glaze",
            "readyInMinutes": 13,
            "servings": 6,
            "image": "Baked-Pumpkin-Donuts-with-Caramel-Glaze-481699.jpg",
            "imageUrls": [
                "Baked-Pumpkin-Donuts-with-Caramel-Glaze-481699.jpg"
            ]
        },
        {
            "id": 476067,
            "title": "Red, White and Blue Baked Donuts",
            "readyInMinutes": 30,
            "servings": 18,
            "image": "Red--White-and-Blue-Baked-Donuts-476067.jpg",
            "imageUrls": [
                "Red--White-and-Blue-Baked-Donuts-476067.jpg"
            ]
        },
        {
            "id": 870341,
            "title": "2-Ingredient Baked Cake Donuts",
            "readyInMinutes": 22,
            "servings": 12,
            "image": "2-ingredient-baked-cake-donuts-870341.jpg",
            "imageUrls": [
                "2-ingredient-baked-cake-donuts-870341.jpg"
            ]
        },
        {
            "id": 502497,
            "title": "Puff Pastry Donuts with Cinnamon Sugar and Bourbon Glaze",
            "readyInMinutes": 45,
            "servings": 10,
            "image": "Puff-Pastry-Donuts-with-Cinnamon-Sugar-and-Bourbon-Glaze-502497.jpg",
            "imageUrls": [
                "Puff-Pastry-Donuts-with-Cinnamon-Sugar-and-Bourbon-Glaze-502497.jpg"
            ]
        },
        {
            "id": 524863,
            "title": "Lemon Coconut Donuts with Lemon Glaze",
            "readyInMinutes": 40,
            "servings": 6,
            "image": "Lemon-Coconut-Donuts-with-Lemon-Glaze-524863.jpg",
            "imageUrls": [
                "Lemon-Coconut-Donuts-with-Lemon-Glaze-524863.jpg"
            ]
        },
        {
            "id": 473549,
            "title": "Baked Coconut Donuts",
            "readyInMinutes": 40,
            "servings": 18,
            "image": "Baked-Coconut-Donuts-473549.jpg",
            "imageUrls": [
                "Baked-Coconut-Donuts-473549.jpg"
            ]
        },
        {
            "id": 678386,
            "title": "Pumpkin Spice, Maple Glazed Apple Fritters",
            "readyInMinutes": 90,
            "servings": 16,
            "image": "Pumpkin-Spice--Maple-Glazed-Apple-Fritters-678386.jpg",
            "imageUrls": [
                "Pumpkin-Spice--Maple-Glazed-Apple-Fritters-678386.jpg"
            ]
        },
        {
            "id": 483287,
            "title": "Apple Cider Donuts with Brown Sugar Topping",
            "readyInMinutes": 25,
            "servings": 12,
            "image": "Apple-Cider-Donuts-with-Brown-Sugar-Topping-483287.jpg",
            "imageUrls": [
                "Apple-Cider-Donuts-with-Brown-Sugar-Topping-483287.jpg"
            ]
        },
        {
            "id": 48097,
            "title": "Apple Cider Doughnuts",
            "readyInMinutes": 45,
            "servings": 4,
            "image": "apple_cider_doughnuts-48097.jpg",
            "imageUrls": [
                "apple_cider_doughnuts-48097.jpg",
                "apple-cider-doughnuts-2-48097.jpg"
            ]
        },
        {
            "id": 812839,
            "title": "Toffee Crunch Donuts",
            "readyInMinutes": 45,
            "servings": 3,
            "image": "toffee-crunch-donuts-812839.jpg",
            "imageUrls": [
                "toffee-crunch-donuts-812839.jpg"
            ]
        },
        {
            "id": 794720,
            "title": "Baked Apple Fritters",
            "readyInMinutes": 27,
            "servings": 32,
            "image": "baked-apple-fritters-794720.jpg",
            "imageUrls": [
                "baked-apple-fritters-794720.jpg"
            ]
        },
        {
            "id": 611684,
            "title": "Peanut Butter Cheesecake Doughnuts with Salted Chocolate Bourbon Caramel",
            "readyInMinutes": 150,
            "servings": 20,
            "image": "Peanut-Butter-Cheesecake-Doughnuts-with-Salted-Chocolate-Bourbon-Caramel-611684.jpg",
            "imageUrls": [
                "Peanut-Butter-Cheesecake-Doughnuts-with-Salted-Chocolate-Bourbon-Caramel-611684.jpg"
            ]
        },
        {
            "id": 489453,
            "title": "Cherry Doughnuts for Valentine’s Day",
            "readyInMinutes": 20,
            "servings": 12,
            "image": "Cherry-Doughnuts-for-Valentines-Day-489453.jpg",
            "imageUrls": [
                "Cherry-Doughnuts-for-Valentines-Day-489453.jpg"
            ]
        },
        {
            "id": 524707,
            "title": "Sweet Potato Pecan Pie Doughnuts with Roasted Pecan Crunch",
            "readyInMinutes": 60,
            "servings": 10,
            "image": "sweet-potato-pecan-pie-doughnuts-with-roasted-pecan-crunch-524707.jpg",
            "imageUrls": [
                "sweet-potato-pecan-pie-doughnuts-with-roasted-pecan-crunch-524707.jpg"
            ]
        },
        {
            "id": 813783,
            "title": "Mini Donuts",
            "readyInMinutes": 45,
            "servings": 24,
            "image": "mini-donuts-813783.jpg",
            "imageUrls": [
                "mini-donuts-813783.jpg"
            ]
        },
        {
            "id": 598021,
            "title": "Bacon Fried Chicken & Donuts",
            "readyInMinutes": 45,
            "servings": 8,
            "image": "Bacon-Fried-Chicken---Donuts-598021.png",
            "imageUrls": [
                "Bacon-Fried-Chicken---Donuts-598021.png"
            ]
        },
        {
            "id": 853423,
            "title": "HG's Iced Pumpkin Spice Donuts",
            "readyInMinutes": 25,
            "servings": 6,
            "image": "hgs-iced-pumpkin-spice-donuts-853423.jpg",
            "imageUrls": [
                "hgs-iced-pumpkin-spice-donuts-853423.jpg"
            ]
        },
        {
            "id": 586530,
            "title": "Brownie Donuts with Fluffy Peanut Butter Frosting",
            "readyInMinutes": 35,
            "servings": 6,
            "image": "Brownie-Donuts-with-Fluffy-Peanut-Butter-Frosting-586530.jpg",
            "imageUrls": [
                "Brownie-Donuts-with-Fluffy-Peanut-Butter-Frosting-586530.jpg"
            ]
        },
        {
            "id": 615937,
            "title": "Baked Vanilla-Glazed Donut Holes",
            "readyInMinutes": 30,
            "servings": 30,
            "image": "Baked-Vanilla-Glazed-Donut-Holes-615937.jpg",
            "imageUrls": [
                "Baked-Vanilla-Glazed-Donut-Holes-615937.jpg"
            ]
        },
        {
            "id": 608223,
            "title": "Cookies and Cream Donuts",
            "readyInMinutes": 45,
            "servings": 8,
            "image": "Cookies-and-Cream-Donuts-608223.jpg",
            "imageUrls": [
                "Cookies-and-Cream-Donuts-608223.jpg"
            ]
        },
        {
            "id": 583416,
            "title": "Pumpkin Spice Latte Donuts #SundaySupper",
            "readyInMinutes": 35,
            "servings": 24,
            "image": "Pumpkin-Spice-Latte-Donuts--SundaySupper-583416.jpg",
            "imageUrls": [
                "Pumpkin-Spice-Latte-Donuts--SundaySupper-583416.jpg"
            ]
        },
        {
            "id": 775666,
            "title": "Easy Homemade Apple Fritters",
            "readyInMinutes": 30,
            "servings": 12,
            "image": "easy-homemade-apple-fritters-775666.jpg",
            "imageUrls": [
                "easy-homemade-apple-fritters-775666.jpg"
            ]
        },
        {
            "id": 540254,
            "title": "Gluten Free Baked Pumpkin Chocolate Chip Doughnuts",
            "readyInMinutes": 45,
            "servings": 8,
            "image": "gluten-free-baked-pumpkin-chocolate-chip-doughnuts-540254.jpg",
            "imageUrls": [
                "gluten-free-baked-pumpkin-chocolate-chip-doughnuts-540254.jpg",
                "Gluten-Free-Baked-Pumpkin-Chocolate-Chip-Doughnuts-540254.jpg"
            ]
        },
        {
            "id": 553133,
            "title": "Baked chai donuts",
            "readyInMinutes": 30,
            "servings": 10,
            "image": "Baked-chai-donuts-553133.png",
            "imageUrls": [
                "Baked-chai-donuts-553133.png"
            ]
        },
        {
            "id": 603061,
            "title": "Best Baked Donut",
            "readyInMinutes": 24,
            "servings": 12,
            "image": "Best-Baked-Donut-603061.jpg",
            "imageUrls": [
                "Best-Baked-Donut-603061.jpg"
            ]
        },
        {
            "id": 669471,
            "title": "Old Fashioned Buttermilk Donuts",
            "readyInMinutes": 45,
            "servings": 15,
            "image": "Old-Fashioned-Buttermilk-Donuts-669471.jpg",
            "imageUrls": [
                "Old-Fashioned-Buttermilk-Donuts-669471.jpg"
            ]
        },
        {
            "id": 559727,
            "title": "Baked S'mores Doughnuts",
            "readyInMinutes": 35,
            "servings": 6,
            "image": "Baked-Smores-Doughnuts-559727.jpg",
            "imageUrls": [
                "Baked-Smores-Doughnuts-559727.jpg"
            ]
        },
        {
            "id": 249537,
            "title": "Coconut Vanilla Gluten-Free Donuts",
            "readyInMinutes": 30,
            "servings": 6,
            "image": "Coconut-Vanilla-Gluten-Free-Donuts-249537.jpg",
            "imageUrls": [
                "Coconut-Vanilla-Gluten-Free-Donuts-249537.jpg"
            ]
        },
        {
            "id": 729111,
            "title": "Oreo Cheesecake Doughnuts",
            "readyInMinutes": 35,
            "servings": 8,
            "image": "oreo-cheesecake-doughnuts-729111.jpg",
            "imageUrls": [
                "oreo-cheesecake-doughnuts-729111.jpg"
            ]
        },
        {
            "id": 720209,
            "title": "Vanilla Bean Glazed Honey Cake Doughnuts",
            "readyInMinutes": 25,
            "servings": 6,
            "image": "vanilla-bean-glazed-honey-cake-doughnuts-720209.jpg",
            "imageUrls": [
                "vanilla-bean-glazed-honey-cake-doughnuts-720209.jpg"
            ]
        },
        {
            "id": 549854,
            "title": "Mini Brown Sugar Glazed Graham Cracker Doughnuts",
            "readyInMinutes": 720,
            "servings": 24,
            "image": "Mini-Brown-Sugar-Glazed-Graham-Cracker-Doughnuts-549854.jpg",
            "imageUrls": [
                "Mini-Brown-Sugar-Glazed-Graham-Cracker-Doughnuts-549854.jpg"
            ]
        },
        {
            "id": 446521,
            "title": "Boston Cream Dessert Cups",
            "readyInMinutes": 160,
            "servings": 24,
            "image": "Boston-Cream-Dessert-Cups-446521.jpg",
            "imageUrls": [
                "Boston-Cream-Dessert-Cups-446521.jpg"
            ]
        },
        {
            "id": 587199,
            "title": "Eggless Carrot Cake Doughnuts with Cream Cheese Frosting",
            "readyInMinutes": 50,
            "servings": 8,
            "image": "Eggless-Carrot-Cake-Doughnuts-with-Cream-Cheese-Frosting-587199.jpg",
            "imageUrls": [
                "Eggless-Carrot-Cake-Doughnuts-with-Cream-Cheese-Frosting-587199.jpg"
            ]
        }
    ],
    "baseUri": "https://spoonacular.com/recipeImages/",
    "offset": 0,
    "number": 100,
    "totalResults": 984,
    "processingTimeMs": 44,
    "expires": 1546132693276
}
